aggregate/__init__.py
aggregate/agg_magics.py
aggregate/bounds.py
aggregate/constants.py
aggregate/decl_pygments.py
aggregate/distributions.py
aggregate/parser.py
aggregate/portfolio.py
aggregate/random_agg.py
aggregate/spectral.py
aggregate/underwriter.py
aggregate/utilities.py
aggregate/agg/test_suite.agg
aggregate/extensions/__init__.py
aggregate/extensions/basic.py
aggregate/extensions/bodoff.py
aggregate/extensions/case_studies.py
aggregate/extensions/cnc.py
aggregate/extensions/discrete.py
aggregate/extensions/figures.py
aggregate/extensions/ft.py
aggregate/extensions/hs.py
aggregate/extensions/pentagon.py
aggregate/extensions/pir_figures.py
aggregate/extensions/risk_progression.py
aggregate/extensions/samples.py
aggregate/extensions/tame.py
aggregate/extensions/test_suite.py
aggregate/extensions/tweedie.py
aggregate/sly/__init__.py
aggregate/sly/ast.py
aggregate/sly/docparse.py
aggregate/sly/lex.py
aggregate/sly/yacc.py
aggregate/templates/Reserve_specification.html
aggregate/templates/Reserve_specification.md
aggregate/templates/Reserve_story.html
aggregate/templates/Reserve_story.md
aggregate/templates/apple-touch-icon.png
aggregate/templates/base.html
aggregate/templates/favicon-16x16.png
aggregate/templates/favicon-32x32.png
aggregate/templates/favicon.ico
aggregate/templates/results_base.html
aggregate/templates/results_extended.html
aggregate/templates/test_suite_template.html
aggregate-0.27.0.dist-info/licenses/LICENSE
aggregate-0.27.0.dist-info/METADATA
aggregate-0.27.0.dist-info/WHEEL
aggregate-0.27.0.dist-info/entry_points.txt
aggregate-0.27.0.dist-info/top_level.txt
aggregate-0.27.0.dist-info/RECORD
