Metadata-Version: 2.4
Name: aggregate
Version: 0.27.0
Summary: Tools for creating and working with aggregate probability distributions.
Author-email: "Stephen J. Mildenhall" <steve@convexrisk.com>
Maintainer-email: "Stephen J. Mildenhall" <steve@convexrisk.com>
License-Expression: BSD-3-Clause
Project-URL: Documentation, https://aggregate.readthedocs.io/en/latest/
Project-URL: Source Code, https://github.com/mynl/aggregate
Classifier: Development Status :: 4 - Beta
Classifier: Intended Audience :: Education
Classifier: Intended Audience :: Financial and Insurance Industry
Classifier: Programming Language :: Python :: 3
Classifier: Programming Language :: Python :: 3.10
Classifier: Programming Language :: Python :: 3.11
Classifier: Programming Language :: Python :: 3.12
Classifier: Topic :: Education
Classifier: Topic :: Office/Business :: Financial
Classifier: Topic :: Scientific/Engineering :: Mathematics
Requires-Python: >=3.10
License-File: LICENSE
Requires-Dist: IPython
Requires-Dist: cycler
Requires-Dist: ipykernel
Requires-Dist: jinja2
Requires-Dist: matplotlib>=3.5
Requires-Dist: numpy>=1.26
Requires-Dist: pandas>=2.1
Requires-Dist: psutil
Requires-Dist: Pygments
Requires-Dist: scipy>=1.11
Provides-Extra: dev
Requires-Dist: docutils<0.17; extra == "dev"
Requires-Dist: jupyter-sphinx; extra == "dev"
Requires-Dist: nbsphinx; extra == "dev"
Requires-Dist: pickleshare; extra == "dev"
Requires-Dist: recommonmark>=0.7.1; extra == "dev"
Requires-Dist: setuptools>=62.3.2; extra == "dev"
Requires-Dist: sphinx>=5.0; extra == "dev"
Requires-Dist: sphinx-panels; extra == "dev"
Requires-Dist: sphinx-rtd-dark-mode; extra == "dev"
Requires-Dist: sphinxcontrib-bibtex; extra == "dev"
Requires-Dist: sphinx-copybutton; extra == "dev"
Requires-Dist: sphinx-toggleprompt; extra == "dev"
Requires-Dist: sphinx-multitoc-numbering; extra == "dev"
Dynamic: license-file
